qlik_sense/__init__.py
qlik_sense/clients/__init__.py
qlik_sense/clients/base.py
qlik_sense/clients/ntlm_client.py
qlik_sense/clients/ssl_client.py
qlik_sense/models/__init__.py
qlik_sense/models/app.py
qlik_sense/models/base.py
qlik_sense/models/custom_property.py
qlik_sense/models/stream.py
qlik_sense/models/tag.py
qlik_sense/models/user.py
qlik_sense/services/__init__.py
qlik_sense/services/app.py
qlik_sense/services/base.py
qlik_sense/services/stream.py
qlik_sense/services/user.py
qlik_sense/services/util.py
qlik_sense-0.2.1.dist-info/LICENSE
qlik_sense-0.2.1.dist-info/WHEEL
qlik_sense-0.2.1.dist-info/METADATA
qlik_sense-0.2.1.dist-info/RECORD
